dataset_pipe/__init__.py
dataset_pipe/config.py
dataset_pipe/dataset.py
dataset_pipe/decoder_list.py
dataset_pipe/encoder_list.py
dataset_pipe/generator.py
dataset_pipe/input.py
dataset_pipe/output.py
dataset_pipe/encoders/__init__.py
dataset_pipe/encoders/binary_encoder.py
dataset_pipe/encoders/dict_to_binary_encoder.py
dataset_pipe/encoders/dummy_encoders.py
dataset_pipe/encoders/one_hot_encoder.py
dataset_pipe/encoders/sparse_word2idx_encoder.py
dataset_pipe/encoders/__pycache__/__init__.cpython-37.pyc
dataset_pipe/encoders/__pycache__/dict_to_binary_encoder.cpython-37.pyc
dataset_pipe/encoders/__pycache__/dummy_encoders.cpython-37.pyc
dataset_pipe/encoders/__pycache__/one_hot_encoder.cpython-37.pyc
dataset_pipe/encoders/__pycache__/sparse_word2idx_encoder.cpython-37.pyc
dataset_pipe/encoders/math/__init__.py
dataset_pipe/encoders/math/ops.py
dataset_pipe/encoders/math/__pycache__/__init__.cpython-37.pyc
dataset_pipe/encoders/math/__pycache__/ops.cpython-37.pyc
dataset_pipe/feeds/__init__.py
dataset_pipe/feeds/base.py
dataset_pipe/feeds/datasets.py
dataset_pipe/feeds/__pycache__/__init__.cpython-37.pyc
dataset_pipe/feeds/__pycache__/base.cpython-37.pyc
dataset_pipe/feeds/__pycache__/datasets.cpython-37.pyc
dataset_pipe/readers/__init__.py
dataset_pipe/readers/csv_reader.py
dataset_pipe/readers/file_reader.py
dataset_pipe/readers/json_reader.py
dataset_pipe/readers/__pycache__/__init__.cpython-37.pyc
dataset_pipe/readers/__pycache__/csv_reader.cpython-37.pyc
dataset_pipe/readers/__pycache__/file_reader.cpython-37.pyc
dataset_pipe/readers/__pycache__/json_reader.cpython-37.pyc
dataset_pipe/utils/method.py
dataset_pipe/utils/__pycache__/method.cpython-37.pyc
dataset_pipe-0.7.7.dist-info/METADATA
dataset_pipe-0.7.7.dist-info/WHEEL
dataset_pipe-0.7.7.dist-info/top_level.txt
dataset_pipe-0.7.7.dist-info/RECORD
