Metadata-Version: 2.1
Name: dataset-pipe
Version: 0.7.7
Summary: Utils for encoding and data set reading
Home-page: https://github.com/atompie/tensorflow-dataset-pipe
Author: Risto Kowaczewski
Author-email: risto.kowaczewski@gmail.com
License: UNKNOWN
Platform: UNKNOWN
Classifier: Programming Language :: Python :: 3
Classifier: License :: OSI Approved :: MIT License
Classifier: Operating System :: OS Independent
Requires-Dist: tensorflow
Requires-Dist: numba
